ankorstore_api_wrapper
