Metadata-Version: 2.1
Name: ankorstore-api-wrapper
Version: 0.0.3
Summary: A simple api wrapper for ankorstore brands
Home-page: https://github.com/sathouel/ankorstore-api-wrapper.git
Author: Steven Athouel
Author-email: sathouel@gmail.com
License: UNKNOWN
Platform: UNKNOWN
Classifier: Programming Language :: Python :: 3
Classifier: License :: OSI Approved :: MIT License
Classifier: Operating System :: OS Independent
Requires-Python: >=3.6
